[{"type":"constructor","payable":false,"inputs":[{"type":"uint256","name":"rate"},{"type":"address","name":"wallet"},{"type":"address","name":"token"},{"type":"uint256","name":"tokenDecimals"}]},{"type":"event","anonymous":false,"name":"OwnershipTransferred","inputs":[{"type":"address","name":"previousOwner","indexed":true},{"type":"address","name":"newOwner","indexed":true}]},{"type":"event","anonymous":false,"name":"Refund","inputs":[{"type":"address","name":"recipient","indexed":false},{"type":"uint256","name":"amount","indexed":false}]},{"type":"event","anonymous":false,"name":"TokensPurchased","inputs":[{"type":"address","name":"purchaser","indexed":false},{"type":"address","name":"beneficiary","indexed":false},{"type":"uint256","name":"value","indexed":false},{"type":"uint256","name":"amount","indexed":false}]},{"type":"function","name":"_contributions","constant":true,"stateMutability":"view","payable":false,"inputs":[{"type":"address"}],"outputs":[{"type":"uint256"}]},{"type":"function","name":"_getTokenAmount","constant":true,"stateMutability":"view","payable":false,"inputs":[{"type":"uint256","name":"weiAmount"}],"outputs":[{"type":"uint256"}]},{"type":"function","name":"_rate","constant":true,"stateMutability":"view","payable":false,"inputs":[],"outputs":[{"type":"uint256"}]},{"type":"function","name":"_token","constant":true,"stateMutability":"view","payable":false,"inputs":[],"outputs":[{"type":"address"}]},{"type":"function","name":"_wallet","constant":true,"stateMutability":"view","payable":false,"inputs":[],"outputs":[{"type":"address"}]},{"type":"function","name":"_weiRaised","constant":true,"stateMutability":"view","payable":false,"inputs":[],"outputs":[{"type":"uint256"}]},{"type":"function","name":"availableTokensICO","constant":true,"stateMutability":"view","payable":false,"inputs":[],"outputs":[{"type":"uint256"}]},{"type":"function","name":"buyTokens","constant":false,"stateMutability":"payable","payable":true,"inputs":[],"outputs":[]},{"type":"function","name":"checkContribution","constant":true,"stateMutability":"view","payable":false,"inputs":[{"type":"address","name":"addr"}],"outputs":[{"type":"uint256"}]},{"type":"function","name":"endICO","constant":true,"stateMutability":"view","payable":false,"inputs":[],"outputs":[{"type":"uint256"}]},{"type":"function","name":"hardCap","constant":true,"stateMutability":"view","payable":false,"inputs":[],"outputs":[{"type":"uint256"}]},{"type":"function","name":"maxPurchase","constant":true,"stateMutability":"view","payable":false,"inputs":[],"outputs":[{"type":"uint256"}]},{"type":"function","name":"minPurchase","constant":true,"stateMutability":"view","payable":false,"inputs":[],"outputs":[{"type":"uint256"}]},{"type":"function","name":"owner","constant":true,"stateMutability":"view","payable":false,"inputs":[],"outputs":[{"type":"address"}]},{"type":"function","name":"refundMe","constant":false,"payable":false,"inputs":[],"outputs":[]},{"type":"function","name":"refundStartDate","constant":true,"stateMutability":"view","payable":false,"inputs":[],"outputs":[{"type":"uint256"}]},{"type":"function","name":"setAvailableTokens","constant":false,"payable":false,"inputs":[{"type":"uint256","name":"amount"}],"outputs":[]},{"type":"function","name":"setHardCap","constant":false,"payable":false,"inputs":[{"type":"uint256","name":"value"}],"outputs":[]},{"type":"function","name":"setMaxPurchase","constant":false,"payable":false,"inputs":[{"type":"uint256","name":"value"}],"outputs":[]},{"type":"function","name":"setMinPurchase","constant":false,"payable":false,"inputs":[{"type":"uint256","name":"value"}],"outputs":[]},{"type":"function","name":"setRate","constant":false,"payable":false,"inputs":[{"type":"uint256","name":"newRate"}],"outputs":[]},{"type":"function","name":"setSoftCap","constant":false,"payable":false,"inputs":[{"type":"uint256","name":"value"}],"outputs":[]},{"type":"function","name":"setWalletReceiver","constant":false,"payable":false,"inputs":[{"type":"address","name":"newWallet"}],"outputs":[]},{"type":"function","name":"softCap","constant":true,"stateMutability":"view","payable":false,"inputs":[],"outputs":[{"type":"uint256"}]},{"type":"function","name":"startICO","constant":false,"payable":false,"inputs":[{"type":"uint256","name":"endDate"},{"type":"uint256","name":"_minPurchase"},{"type":"uint256","name":"_maxPurchase"},{"type":"uint256","name":"_softCap"},{"type":"uint256","name":"_hardCap"}],"outputs":[]},{"type":"function","name":"startRefund","constant":true,"stateMutability":"view","payable":false,"inputs":[],"outputs":[{"type":"bool"}]},{"type":"function","name":"stopICO","constant":false,"payable":false,"inputs":[],"outputs":[]},{"type":"function","name":"takeTokens","constant":false,"payable":false,"inputs":[{"type":"address","name":"tokenAddress"}],"outputs":[]},{"type":"function","name":"transferOwnership","constant":false,"payable":false,"inputs":[{"type":"address","name":"newOwner"}],"outputs":[]},{"type":"function","name":"weiRaised","constant":true,"stateMutability":"view","payable":false,"inputs":[],"outputs":[{"type":"uint256"}]},{"type":"function","name":"withdraw","constant":false,"payable":false,"inputs":[],"outputs":[]}]